LICENSE
MANIFEST.in
README.md
pyproject.toml
setup.py
OASYS2_SRW.egg-info/PKG-INFO
OASYS2_SRW.egg-info/SOURCES.txt
OASYS2_SRW.egg-info/dependency_links.txt
OASYS2_SRW.egg-info/entry_points.txt
OASYS2_SRW.egg-info/not-zip-safe
OASYS2_SRW.egg-info/requires.txt
OASYS2_SRW.egg-info/top_level.txt
orangecontrib/__init__.py
orangecontrib/srw/__init__.py
orangecontrib/srw/menu/__init__.py
orangecontrib/srw/menu/srw_tools_menu.py
orangecontrib/srw/util/__init__.py
orangecontrib/srw/util/python_script.py
orangecontrib/srw/util/scanning.py
orangecontrib/srw/util/srw_objects.py
orangecontrib/srw/util/srw_util.py
orangecontrib/srw/widgets/__init__.py
orangecontrib/srw/widgets/gui/__init__.py
orangecontrib/srw/widgets/gui/ow_srw_absorber.py
orangecontrib/srw/widgets/gui/ow_srw_crystal.py
orangecontrib/srw/widgets/gui/ow_srw_grating.py
orangecontrib/srw/widgets/gui/ow_srw_mirror.py
orangecontrib/srw/widgets/gui/ow_srw_optical_element.py
orangecontrib/srw/widgets/gui/ow_srw_power_density_viewer.py
orangecontrib/srw/widgets/gui/ow_srw_source.py
orangecontrib/srw/widgets/gui/ow_srw_wavefront_viewer.py
orangecontrib/srw/widgets/gui/ow_srw_widget.py
orangecontrib/srw/widgets/gui/misc/crystal_usage.png
orangecontrib/srw/widgets/gui/misc/dabam_height_profile_usage.png
orangecontrib/srw/widgets/gui/misc/height_error_profile_usage.png
orangecontrib/srw/widgets/gui/misc/propagator_info.png
orangecontrib/srw/widgets/gui/misc/reflectivity_generator_usage.png
orangecontrib/srw/widgets/light_sources/__init__.py
orangecontrib/srw/widgets/light_sources/ow_srw_3d_light_source.py
orangecontrib/srw/widgets/light_sources/ow_srw_bending_magnet.py
orangecontrib/srw/widgets/light_sources/ow_srw_gaussian_source.py
orangecontrib/srw/widgets/light_sources/ow_srw_power_density.py
orangecontrib/srw/widgets/light_sources/ow_srw_radiation.py
orangecontrib/srw/widgets/light_sources/ow_srw_spectrum.py
orangecontrib/srw/widgets/light_sources/ow_srw_undulator.py
orangecontrib/srw/widgets/light_sources/icons/3d.png
orangecontrib/srw/widgets/light_sources/icons/bending_magnet.png
orangecontrib/srw/widgets/light_sources/icons/gaussian_source.png
orangecontrib/srw/widgets/light_sources/icons/power_density.png
