Metadata-Version: 2.4
Name: OASYS2-SRW
Version: 1.0.6
Summary: SRW in OASYS2
Home-page: https://github.com/lucarebuffi/OASYS-SRW
Download-URL: https://github.com/lucarebuffi/OASYS-SRW
Author: Luca Rebuffi
Author-email: lrebuffi@anl.gov
License: GPLv3
Keywords: waveoptics,simulator,oasys2
Classifier: Development Status :: 5 - Production/Stable
Classifier: Environment :: X11 Applications :: Qt
Classifier: Environment :: Console
Classifier: Environment :: Plugins
Classifier: Programming Language :: Python :: 3
Classifier: Intended Audience :: Science/Research
License-File: LICENSE
Requires-Dist: oasys2>=0.0.7
Requires-Dist: syned-gui-2>=1.0.3
Requires-Dist: wofrysrw>=1.1.34
Requires-Dist: xoppylib>=1.0.43
Requires-Dist: srwpy==4.1.1
Requires-Dist: scikit-image
Dynamic: author
Dynamic: author-email
Dynamic: classifier
Dynamic: description
Dynamic: download-url
Dynamic: home-page
Dynamic: keywords
Dynamic: license
Dynamic: license-file
Dynamic: requires-dist
Dynamic: summary
